{
	"JIANGXIAOMOD-JIANG_XIAO.title": "江曉",
	"JIANGXIAOMOD-JIANG_XIAO.titleObject": "江曉",
	"JIANGXIAOMOD-JIANG_XIAO.description": "來自[gold][九星毒奶][/gold]的醫療系星武者，擅長治癒與戰術干擾，本人醫療系卻武器技藝精通。",
	"JIANGXIAOMOD-JIANG_XIAO.pronounObject": "他",
	"JIANGXIAOMOD-JIANG_XIAO.possessiveAdjective": "他的",
	"JIANGXIAOMOD-JIANG_XIAO.pronounPossessive": "他的",
	"JIANGXIAOMOD-JIANG_XIAO.pronounSubject": "他",
	"JIANGXIAOMOD-JIANG_XIAO.goldMonologue": "這點錢...夏研給的都比這多。",
	"JIANGXIAOMOD-JIANG_XIAO.eventDeathPrevention": "夕梦朝拾，如夢一場。",
	"JIANGXIAOMOD-JIANG_XIAO.aromaPrinciple": "醫者仁心",
	"JIANGXIAOMOD-JIANG_XIAO.cardsModifierTitle": "江曉卡牌",
	"JIANGXIAOMOD-JIANG_XIAO.cardsModifierDescription": "江曉的卡片現在會出現在獎勵與商店中。",
	"JIANGXIAOMOD-JIANG_XIAO.banter.alive.endTurnPing": "就這?",
    "JIANGXIAOMOD-JIANG_XIAO.banter.dead.endTurnPing": "自負的代價..."
}